Metadata-Version: 2.1
Name: pycomponent
Version: 0.2201.0
Summary: pycomponent: components for python
Home-page: https://github.com/DIYer22/pycomponent
Author: DIYer22
Author-email: ylxx@live.com
License: UNKNOWN
Platform: UNKNOWN
Classifier: Topic :: Software Development :: Libraries :: Python Modules
Classifier: Programming Language :: Python :: 3
Classifier: License :: OSI Approved :: MIT License
Classifier: Operating System :: OS Independent
